yatbaf/__init__.py
yatbaf/__main__.py
yatbaf/abc.py
yatbaf/bot.py
yatbaf/di.py
yatbaf/dispatcher.py
yatbaf/enums.py
yatbaf/exceptions.py
yatbaf/group.py
yatbaf/handler.py
yatbaf/long_polling.py
yatbaf/py.typed
yatbaf/state.py
yatbaf/storage.py
yatbaf/typing.py
yatbaf/utils.py
yatbaf/version.py
yatbaf/warnings.py
yatbaf/client/__init__.py
yatbaf/client/http.py
yatbaf/client/models.py
yatbaf/client/telegram.py
yatbaf/client/utils.py
yatbaf/filters/__init__.py
yatbaf/filters/base.py
yatbaf/filters/callback_data.py
yatbaf/filters/chat_id.py
yatbaf/filters/command.py
yatbaf/filters/content_type.py
yatbaf/filters/conversation.py
yatbaf/filters/text_content.py
yatbaf/filters/user.py
yatbaf/helpers/__init__.py
yatbaf/helpers/conversation.py
yatbaf/helpers/deeplink.py
yatbaf/helpers/md.py
yatbaf/helpers/middleware.py
yatbaf/methods/__init__.py
yatbaf/methods/abc.py
yatbaf/methods/add_sticker_to_set.py
yatbaf/methods/answer_callback_query.py
yatbaf/methods/answer_inline_query.py
yatbaf/methods/answer_pre_checkout_query.py
yatbaf/methods/answer_shipping_query.py
yatbaf/methods/answer_web_app_query.py
yatbaf/methods/approve_chat_join_request.py
yatbaf/methods/ban_chat_member.py
yatbaf/methods/ban_chat_sender_chat.py
yatbaf/methods/close.py
yatbaf/methods/close_forum_topic.py
yatbaf/methods/close_general_forum_topic.py
yatbaf/methods/copy_message.py
yatbaf/methods/copy_messages.py
yatbaf/methods/create_chat_invite_link.py
yatbaf/methods/create_forum_topic.py
yatbaf/methods/create_invoice_link.py
yatbaf/methods/create_new_sticker_set.py
yatbaf/methods/decline_chat_join_request.py
yatbaf/methods/delete_chat_photo.py
yatbaf/methods/delete_chat_sticker_set.py
yatbaf/methods/delete_forum_topic.py
yatbaf/methods/delete_message.py
yatbaf/methods/delete_messages.py
yatbaf/methods/delete_my_commands.py
yatbaf/methods/delete_sticker_from_set.py
yatbaf/methods/delete_sticker_set.py
yatbaf/methods/delete_webhook.py
yatbaf/methods/edit_chat_invite_link.py
yatbaf/methods/edit_forum_topic.py
yatbaf-0.12.0.dist-info/METADATA
yatbaf-0.12.0.dist-info/WHEEL
yatbaf-0.12.0.dist-info/licenses/LICENSE
yatbaf-0.12.0.dist-info/RECORD
