Metadata-Version: 2.3
Name: yatbaf
Version: 0.12.0
Summary: Telegram Bot framework
Project-URL: Source, https://codeberg.org/maraudeur/yatbaf
Author-email: Maraudeur <maraudeur1@protonmail.ch>
License:  The MIT License (MIT)
License-File: LICENSE
Keywords: telegram-bot,telegram-bot-api
Classifier: Development Status :: 4 - Beta
Classifier: Intended Audience :: Developers
Classifier: License :: OSI Approved :: MIT License
Classifier: Programming Language :: Python
Classifier: Programming Language :: Python :: 3
Classifier: Programming Language :: Python :: 3.11
Classifier: Programming Language :: Python :: 3.12
Classifier: Typing :: Typed
Requires-Python: >=3.11
Requires-Dist: httpx<1.0.0,>=0.27.0
Requires-Dist: msgspec<1.0.0,>=0.18.5
Provides-Extra: dev
Requires-Dist: pre-commit<4.0.0,>=3.0.0; extra == 'dev'
Provides-Extra: docs
Requires-Dist: pydata-sphinx-theme<1.0.0,>=0.14.3; extra == 'docs'
Requires-Dist: sphinx-copybutton<1.0.0,>=0.5.2; extra == 'docs'
Requires-Dist: sphinx-design<1.0.0,>=0.5.0; extra == 'docs'
Requires-Dist: sphinx<8.0.0,>=7.2.6; extra == 'docs'
Provides-Extra: lint
Requires-Dist: flake8-bugbear==24.4.21; extra == 'lint'
Requires-Dist: flake8-unused-arguments==0.0.13; extra == 'lint'
Requires-Dist: flake8==7.0.0; extra == 'lint'
Requires-Dist: isort<6.0.0,>=5.13.2; extra == 'lint'
Requires-Dist: mypy==1.9.0; extra == 'lint'
Requires-Dist: yapf==0.40.2; extra == 'lint'
Provides-Extra: test
Requires-Dist: coverage==7.5.0; extra == 'test'
Requires-Dist: pytest-asyncio==0.23.6; extra == 'test'
Requires-Dist: pytest-cov==5.0.0; extra == 'test'
Requires-Dist: pytest-httpx==0.30.0; extra == 'test'
Requires-Dist: pytest<9.0.0,>=8.2.0; extra == 'test'
